dataset_loading/__init__.py
dataset_loading/cifar.py
dataset_loading/core.py
dataset_loading/mnist.py
dataset_loading/pascal.py
dataset_loading/tensorboard_logging.py
dataset_loading/utils.py
dataset_loading/imagenet/__init__.py
dataset_loading/imagenet/cls_loc.py
finn_dataset_loading-0.0.5.dist-info/LICENSE
finn_dataset_loading-0.0.5.dist-info/METADATA
finn_dataset_loading-0.0.5.dist-info/WHEEL
finn_dataset_loading-0.0.5.dist-info/top_level.txt
finn_dataset_loading-0.0.5.dist-info/RECORD
