Metadata-Version: 2.1
Name: finn-dataset-loading
Version: 0.0.5
Summary: Loading image datasets using queues.
Home-page: https://github.com/fbcotter/dataset_loading.git
Author: Fergal Cotter
Author-email: fbc23@cam.ac.uk
License: MIT
Keywords: image datasets,cifar,pascal,mnist,imagenet
Platform: UNKNOWN
Classifier: Programming Language :: Python :: 3
Classifier: Intended Audience :: Developers
Classifier: License :: OSI Approved :: MIT License
Classifier: Topic :: Software Development :: Libraries
Classifier: Topic :: Utilities
Requires-Dist: Pillow
Requires-Dist: scipy
